{
 "questions": {
  "fp-01": {
   "q": "만년필로 써도 안 번지는 노트 추천해줘",
   "kw": "만년필노트",
   "line": "잉크파인(만년필종이)",
   "mentioned": false,
   "searchQueries": [
    "만년필 안 번지는 노트 추천",
    "만년필 번짐 없는 종이",
    "fountain pen friendly notebooks Korea"
   ],
   "brands": [
    "로디아 (Rhodia)",
    "클레르퐁텐 (Clairefontaine)",
    "호보니치 테초 (Hobonichi Techo)",
    "고쿠요 캠퍼스 (Kokuyo Campus)",
    "그래필로 (Graphilo)",
    "레타이 (Leatai)",
    "옥스포드 (Oxford)"
   ],
   "sources": [
    {
     "kind": "티스토리",
     "title": "tistory.com",
     "url": "https://self-cure.tistory.com/31"
    },
    {
     "kind": "유튜브",
     "title": "youtube.com",
     "url": "https://www.youtube.com/watch?v=2vqIi4JzH9g"
    },
    {
     "kind": "웹/블로그",
     "title": "gentlemanstationer.com",
     "url": "https://www.gentlemanstationer.com/blog/2021/3/10/hierarchies-of-fountain-pen-friendly-paper"
    },
    {
     "kind": "티스토리",
     "title": "tistory.com",
     "url": "https://afterview.tistory.com/entry/%EB%A7%8C%EB%85%84%ED%95%84-%EB%85%B8%ED%8A%B8-%EB%B9%84%EA%B5%90%EB%9D%BC%EC%9D%B4%ED%94%84-%EA%B3%A0%EC%BF%A0%EC%9A%94-%EB%A7%88%EB%A3%A8%EB%A7%9D-%ED%81%B4%EB%A0%88%EB%A5%B4%ED%90%81%ED%85%90-%EA%B0%81%EB%8B%B7-%EC%95%84%EB%A5%B4%EB%94%94%EC%9B%80"
    },
    {
     "kind": "웹/블로그",
     "title": "thejournalshop.com",
     "url": "https://www.thejournalshop.com/collections/iconic"
    },
    {
     "kind": "웹/블로그",
     "title": "rediscoveranalog.com",
     "url": "https://rediscoveranalog.com/fountain-pen-friendly-notebooks-that-arent-rhodia-or-tomoe-river/"
    },
    {
     "kind": "웹/블로그",
     "title": "darkerdum.com",
     "url": "https://darkerdum.com/%EB%A7%8C%EB%85%84%ED%95%84%EC%9A%A9-%EB%82%B1%EC%9E%A5-%EC%A2%85%EC%9D%B4-%EC%B6%94%EC%B2%9C-%EB%B0%8F-%EA%B5%AC%EB%A7%A4-%EB%B0%A9%EB%B2%95/"
    },
    {
     "kind": "웹/블로그",
     "title": "moonkoo.com",
     "url": "https://moonkoo.com/products/fig-notebook-101-blank-fountain-pen-friendly-copy-1"
    }
   ]
  },
  "fp-02": {
   "q": "만년필로 쓰기 좋은 다이어리 추천해줘",
   "kw": "만년필다이어리",
   "line": "잉크파인(만년필종이)",
   "mentioned": true,
   "searchQueries": [
    "만년필 친화적인 다이어리 추천",
    "만년필 사용 시 번짐 없는 다이어리",
    "만년필용 종이 품질 좋은 다이어리",
    "다이어리 만년필 잉크 비침",
    "만년필용 다이어리 브랜드 추천"
   ],
   "brands": [
    "만년필 다이어리 선택 시 고려 사항",
    "종이 무게 (평량)",
    "종이 코팅",
    "잉크 번짐과 비침",
    "제본 방식",
    "만년필 친화적인 다이어리 및 용지 추천",
    "미도리 MD (Midori MD)",
    "로이텀 1917 (LEUCHTTURM1917)"
   ],
   "sources": [
    {
     "kind": "티스토리",
     "title": "tistory.com",
     "url": "https://1jeongbo.tistory.com/entry/%EB%A7%8C%EB%85%84%ED%95%84%EB%A1%9C-%EC%93%B0%EB%8A%94-%EB%8B%A4%EC%9D%B4%EC%96%B4%EB%A6%AC-%EA%B0%80%EC%9D%B4%EB%93%9C-%EC%9E%89%ED%81%AC-%EB%B2%88%EC%A7%90-%EC%97%86%EC%9D%B4-%EC%99%84%EC%84%B1%ED%95%98%EB%8A%94-%EB%B0%A9%EB%B2%95"
    },
    {
     "kind": "유튜브",
     "title": "youtube.com",
     "url": "https://www.youtube.com/watch?v=HzMRqPKhuuU"
    },
    {
     "kind": "레딧",
     "title": "reddit.com",
     "url": "https://www.reddit.com/r/fountainpens/comments/1e75egf/favorite_high_quality_journals_that_dont_bleed/?tl=ko"
    },
    {
     "kind": "레딧",
     "title": "reddit.com",
     "url": "https://www.reddit.com/r/fountainpens/comments/1hkwkaw/what_is_the_best_paper_for_fountain_pens/?tl=ko"
    },
    {
     "kind": "웹/블로그",
     "title": "leatai.com",
     "url": "https://leatai.com/ko/%EB%85%B8%ED%8A%B8%EB%B6%81-%EC%A7%80%EC%8B%9D/%EB%A7%8C%EB%85%84%ED%95%84-%EB%85%B8%ED%8A%B8-%EC%84%A0%ED%83%9D-3%EA%B0%80%EC%A7%80-%ED%8C%81-%EB%B6%80%EB%93%9C%EB%9F%AC%EC%9A%B4-%ED%95%84%EA%B8%B0%EC%99%80-%EB%B2%88%EC%A7%90-%EB%B0%A9%EC%A7%80/"
    },
    {
     "kind": "웹/블로그",
     "title": "youcan-doit.co.kr",
     "url": "https://youcan-doit.co.kr/entry/%EB%A7%8C%EB%85%84%ED%95%84-%EB%8B%A4%EC%9D%B4%EC%96%B4%EB%A6%AC-%EC%B6%94%EC%B2%9C-%EB%AF%B8%EB%8F%84%EB%A6%AC-vs-%EB%A1%9C%EC%9D%B4%ED%85%80feat%EB%AA%B0%EC%8A%A4%ED%82%A8"
    },
    {
     "kind": "유튜브",
     "title": "youtube.com",
     "url": "https://www.youtube.com/watch?v=NK3nuQLVO28"
    },
    {
     "kind": "티스토리",
     "title": "tistory.com",
     "url": "https://willucy.tistory.com/897"
    }
   ]
  },
  "fp-03": {
   "q": "만년필 쓰기 좋은 종이 추천해줘",
   "kw": "만년필종이",
   "line": "잉크파인(만년필종이)",
   "mentioned": false,
   "searchQueries": [
    "만년필 종이 추천",
    "만년필에 좋은 종이 특징",
    "만년필 번짐 없는 종이",
    "만년필 잉크 흡수 안되는 종이",
    "로디아 만년필",
    "토모에리버 만년필"
   ],
   "brands": [
    "1. 토모에리버 (Tomoe River)",
    "2. 로디아 (Rhodia)",
    "3. 클레르퐁텐 (Clairefontaine)",
    "4. 미도리 MD (Midori MD)",
    "5. 고쿠요 캠퍼스 (KOKUYO Campus)"
   ],
   "sources": [
    {
     "kind": "웹/블로그",
     "title": "darkerdum.com",
     "url": "https://darkerdum.com/%EB%A7%8C%EB%85%84%ED%95%84%EC%9A%A9-%EB%82%B1%EC%9E%A5-%EC%A2%85%EC%9D%B4-%EC%B6%94%EC%B2%9C-%EB%B0%8F-%EA%B5%AC%EB%A7%A4-%EB%B0%A9%EB%B2%95/"
    },
    {
     "kind": "유튜브",
     "title": "youtube.com",
     "url": "https://www.youtube.com/watch?v=HzMRqPKhuuU"
    },
    {
     "kind": "레딧",
     "title": "reddit.com",
     "url": "https://www.reddit.com/r/fountainpens/comments/1hkwkaw/what_is_the_best_paper_for_fountain_pens/?tl=ko"
    },
    {
     "kind": "레딧",
     "title": "reddit.com",
     "url": "https://www.reddit.com/r/fountainpens/comments/l2t870/most_fountain_pen_friendly_paper/?tl=ko"
    },
    {
     "kind": "웹/블로그",
     "title": "hana-haru.com",
     "url": "https://m.hana-haru.com/product/%EB%A1%9C%EA%B7%B8%EB%B6%81-%EB%8F%84%ED%8A%B8%EC%A0%90-%ED%86%A0%EB%AA%A8%EC%97%90%EB%A6%AC%EB%B2%8452g/59/"
    },
    {
     "kind": "웹/블로그",
     "title": "theqoo.net",
     "url": "https://theqoo.net/diy/2543924608"
    },
    {
     "kind": "티스토리",
     "title": "tistory.com",
     "url": "https://self-cure.tistory.com/31"
    },
    {
     "kind": "유튜브",
     "title": "youtube.com",
     "url": "https://www.youtube.com/watch?v=dAOjFFrhze8"
    }
   ]
  },
  "fp-04": {
   "q": "만년필 잉크가 안 번지는 종이 추천해줘",
   "kw": "안번지는만년필종이",
   "line": "잉크파인(만년필종이)",
   "mentioned": false,
   "searchQueries": [
    "만년필 잉크 안 번지는 종이 추천",
    "만년필 친화적인 종이 한국",
    "만년필 종이 종류",
    "종이 평량 만년필"
   ],
   "brands": [
    "토모에 리버 (Tomoe River)",
    "미도리 MD (Midori MD)",
    "로디아 (Rhodia)",
    "클레르퐁텐 (Clairfontaine)",
    "로이텀 (Leuchtturm1917)",
    "아레나 (Arena)",
    "아코팩 (Acropack)",
    "라이프 노블 (Life Noble)"
   ],
   "sources": [
    {
     "kind": "웹/블로그",
     "title": "samwonpaper.com",
     "url": "https://www.samwonpaper.com/blog/%ED%95%84%EC%82%AC-%EB%A7%8C%EB%85%84%ED%95%84-%ED%8E%A0%EB%A6%AC%EC%B9%B8-%EB%9D%BC%EB%AF%B8-%ED%94%8C%EB%9E%98%ED%8B%B0%EB%84%98-%EC%A2%85%EC%9D%B4-%EB%B9%84%EC%BD%94%ED%8C%85/"
    },
    {
     "kind": "레딧",
     "title": "reddit.com",
     "url": "https://www.reddit.com/r/fountainpens/comments/1hkwkaw/what_is_the_best_paper_for_fountain_pens/?tl=ko"
    },
    {
     "kind": "웹/블로그",
     "title": "darkerdum.com",
     "url": "https://darkerdum.com/%EB%A7%8C%EB%85%84%ED%95%84%EC%9A%A9-%EB%82%B1%EC%9E%A5-%EC%A2%85%EC%9D%B4-%EC%B6%94%EC%B2%9C-%EB%B0%8F-%EA%B5%AC%EB%A7%A4-%EB%B0%A9%EB%B2%95/"
    },
    {
     "kind": "유튜브",
     "title": "youtube.com",
     "url": "https://www.youtube.com/watch?v=2ERmnBvbPK4"
    },
    {
     "kind": "유튜브",
     "title": "youtube.com",
     "url": "https://www.youtube.com/watch?v=HzMRqPKhuuU"
    },
    {
     "kind": "레딧",
     "title": "reddit.com",
     "url": "https://www.reddit.com/r/notebooks/comments/1abqlev/unruled_journals_that_can_withstand_fountain_pen/?tl=ko"
    },
    {
     "kind": "티스토리",
     "title": "tistory.com",
     "url": "https://self-cure.tistory.com/31"
    },
    {
     "kind": "카페",
     "title": "daum.net",
     "url": "https://cafe.daum.net/aisitaihito/HJ9M/11?svc=cafeapi"
    }
   ]
  },
  "dy-01": {
   "q": "5년 일기장 추천해줘",
   "kw": "5년일기장",
   "line": "오늘기억 일기",
   "mentioned": true,
   "searchQueries": [
    "5년 일기장 추천",
    "5년 다이어리 인기 순위",
    "5년 저널 추천",
    "best 5 year diary korea"
   ],
   "brands": [
    "가네쉬 5년 다이어리",
    "리훈 5년 다이어리",
    "일상집 5년 일기장 다이어리",
    "Sterling Ink 5년 다이어리"
   ],
   "sources": [
    {
     "kind": "웹/블로그",
     "title": "tokyopenshop.com",
     "url": "https://tokyopenshop.com/products/midori-5-year-diary"
    },
    {
     "kind": "웹/블로그",
     "title": "wellappointeddesk.com",
     "url": "https://www.wellappointeddesk.com/2023/01/planner-review-midori-md-5-year-diaries/"
    },
    {
     "kind": "웹/블로그",
     "title": "gentlemanstationer.com",
     "url": "https://www.gentlemanstationer.com/blog/tag/Midori+5+Year+Diary"
    },
    {
     "kind": "티스토리",
     "title": "tistory.com",
     "url": "https://hoonincome.tistory.com/20"
    },
    {
     "kind": "웹/블로그",
     "title": "wannathis.co.kr",
     "url": "https://wannathis.co.kr/product/%EC%9E%94%EB%AC%BC%EA%B2%B0-5%EB%85%84-%EC%9D%BC%EA%B8%B0%EC%9E%A5-%EB%8B%A4%EC%9D%B4%EC%96%B4%EB%A6%AC/1032/"
    },
    {
     "kind": "유튜브",
     "title": "youtube.com",
     "url": "https://www.youtube.com/watch?v=dpN5GmSVSsM"
    },
    {
     "kind": "유튜브",
     "title": "youtube.com",
     "url": "https://www.youtube.com/watch?v=Jid3nrLOdas"
    },
    {
     "kind": "웹/블로그",
     "title": "oliveyoung.co.kr",
     "url": "https://m.oliveyoung.co.kr/m/G.do?goodsNo=B000000248296"
    }
   ]
  },
  "dy-02": {
   "q": "날짜 없는 만년형 다이어리 추천해줘",
   "kw": "만년다이어리",
   "line": "오늘기억 일기",
   "mentioned": false,
   "searchQueries": [
    "만년형 다이어리 추천",
    "날짜 없는 다이어리 추천",
    "best undated planner korea",
    "perpetual diary recommendations"
   ],
   "brands": [],
   "sources": [
    {
     "kind": "웹/블로그",
     "title": "photobookkorea.com",
     "url": "https://www.photobookkorea.com/stationery/all-year-planner"
    },
    {
     "kind": "웹/블로그",
     "title": "lifelog4.me",
     "url": "https://lifelog4.me/entry/%EB%A7%A4%EB%85%84-1%EC%9B%94%EC%97%90%EB%A7%8C-%EC%93%B0%EA%B3%A0-%EB%B2%84%EB%A6%AC%EB%82%98%EC%9A%94-%F0%9F%98%AD-%EC%8B%A4%ED%8C%A8-%EC%97%86%EB%8A%94-2026-%EB%8B%A4%EC%9D%B4%EC%96%B4%EB%A6%AC-%EC%B6%94%EC%B2%9C"
    },
    {
     "kind": "웹/블로그",
     "title": "ardium.co.kr",
     "url": "https://ardium.co.kr/category/%EB%8B%A4%EC%9D%B4%EC%96%B4%EB%A6%AC-%EC%B6%94%EC%B2%9C/611/"
    },
    {
     "kind": "웹/블로그",
     "title": "fallindesign.com",
     "url": "https://www.fallindesign.com/diaries-planners/"
    },
    {
     "kind": "웹/블로그",
     "title": "livework.net",
     "url": "https://m.livework.net/category/%EB%A7%8C%EB%85%84%ED%98%95/110/"
    },
    {
     "kind": "웹/블로그",
     "title": "kyobobook.co.kr",
     "url": "https://hottracks.kyobobook.co.kr/gift/01/08/01"
    },
    {
     "kind": "웹/블로그",
     "title": "yes24.com",
     "url": "https://event.yes24.com/template?EventNo=255456"
    },
    {
     "kind": "웹/블로그",
     "title": "webudding.com",
     "url": "https://webudding.com/en/store/product/detail/21117/"
    }
   ]
  },
  "dy-03": {
   "q": "감사일기 쓰기 좋은 일기장 추천해줘",
   "kw": "감사일기",
   "line": "오늘기억 일기",
   "mentioned": true,
   "searchQueries": [
    "감사일기장 추천",
    "감사 일기 쓰기 좋은 일기장",
    "best gratitude journals Korea"
   ],
   "brands": [
    "✍️ 아날로그 감사 일기장 추천",
    "자문자답 세 가지 감사 일기 (감사노트, 6개월)",
    "하루 5분 감사 일기",
    "나를 바꾸는 작은 기적, 감사",
    "한 줄의 기적, 감사일기",
    "리훈 오늘기억 하루하루 감사일기",
    "어린이 감사일기 (100일)",
    "📱 디지털 감사 일기 앱 추천"
   ],
   "sources": [
    {
     "kind": "웹/블로그",
     "title": "kyobobook.co.kr",
     "url": "https://search.kyobobook.co.kr/search?keyword=%EA%B0%90%EC%82%AC%EC%9D%BC%EA%B8%B0"
    },
    {
     "kind": "웹/블로그",
     "title": "indigostory.co.kr",
     "url": "https://m.indigostory.co.kr/product/detail.html?product_no=1493&cate_no=0&display_group=5"
    },
    {
     "kind": "유튜브",
     "title": "youtube.com",
     "url": "https://www.youtube.com/watch?v=aNDYsyAa7Ws"
    },
    {
     "kind": "웹/블로그",
     "title": "intelligentchange.com",
     "url": "https://www.intelligentchange.com/collections/journals"
    },
    {
     "kind": "웹/블로그",
     "title": "etsy.com",
     "url": "https://www.etsy.com/listing/1725491889/gratitude-journal-korean-thankful"
    },
    {
     "kind": "웹/블로그",
     "title": "etsy.com",
     "url": "https://www.etsy.com/il-en/listing/1725491889/gratitude-journal-korean-journal-for"
    },
    {
     "kind": "티스토리",
     "title": "tistory.com",
     "url": "https://bosslove.tistory.com/115"
    },
    {
     "kind": "웹/블로그",
     "title": "google.com",
     "url": "https://play.google.com/store/apps/details?id=org.maysnow.gratitudediary&hl=ko"
    }
   ]
  },
  "gb-01": {
   "q": "손으로 쓰는 가계부 추천해줘",
   "kw": "수기가계부",
   "line": "오늘쓰임 가계부",
   "mentioned": false,
   "searchQueries": [
    "손으로 쓰는 가계부 추천",
    "수기 가계부 인기 제품",
    "아날로그 가계부 장점"
   ],
   "brands": [
    "호호양 가계부",
    "맘마미아 가계부",
    "뿌미맘 가계부",
    "샀다치고 가계부",
    "2026 채우다 수기 가계부 (구채희 가계부)",
    "몰입도 상승",
    "자유로운 구성",
    "디지털 피로도 감소"
   ],
   "sources": [
    {
     "kind": "웹/블로그",
     "title": "signalplanner.co.kr",
     "url": "https://blog.signalplanner.co.kr/9536/"
    },
    {
     "kind": "티스토리",
     "title": "tistory.com",
     "url": "https://beaaarich.tistory.com/31"
    },
    {
     "kind": "유튜브",
     "title": "youtube.com",
     "url": "https://www.youtube.com/watch?v=fklys7AbSJU"
    },
    {
     "kind": "웹/블로그",
     "title": "ch9.co.kr",
     "url": "https://ch9.co.kr/category/%EB%8B%A4%EC%9D%B4%EC%96%B4%EB%A6%AC%EC%88%98%EA%B8%B0%EA%B0%80%EA%B3%84%EB%B6%80/55/"
    },
    {
     "kind": "티스토리",
     "title": "tistory.com",
     "url": "https://catbook.tistory.com/entry/%EC%86%90%EC%9C%BC%EB%A1%9C-%EC%9E%91%EC%84%B1%ED%95%98%EB%8A%94-%EC%95%84%EB%82%A0%EB%A1%9C%EA%B7%B8-%EA%B0%80%EA%B3%84%EB%B6%80-%EC%9E%90%EB%9E%91%ED%95%98%EA%B8%B0"
    },
    {
     "kind": "웹/블로그",
     "title": "banksalad.com",
     "url": "https://www.banksalad.com/contents/%EC%9A%B0%EB%A6%AC%EA%B0%80-%EA%B0%80%EA%B3%84%EB%B6%80%EB%A5%BC-%EC%8D%A8%EC%95%BC-%ED%95%98%EB%8A%94-4%EA%B0%80%EC%A7%80-%EC%9D%B4%EC%9C%A0-99ef"
    },
    {
     "kind": "웹/블로그",
     "title": "jobkorea.co.kr",
     "url": "https://www.jobkorea.co.kr/goodjob/tip/view?News_No=15465"
    }
   ]
  },
  "gb-02": {
   "q": "초보도 쓰기 쉬운 가계부 추천해줘",
   "kw": "초보가계부",
   "line": "오늘쓰임 가계부",
   "mentioned": false,
   "searchQueries": [
    "초보 가계부 추천",
    "쉬운 가계부 앱",
    "간단한 가계부",
    "가장 쉬운 가계부",
    "가계부 어플 추천 초보"
   ],
   "brands": [
    "뱅크샐러드 (Bank Salad)",
    "편한가계부",
    "토스 (Toss)",
    "머니플랜 (Money Plan)",
    "똑똑 가계부",
    "간단 가계부",
    "카카오페이 가계부",
    "수기 가계부"
   ],
   "sources": [
    {
     "kind": "티스토리",
     "title": "tistory.com",
     "url": "https://raradiane.tistory.com/entry/%EC%9E%AC%ED%85%8C%ED%81%AC-%EC%B4%88%EB%B3%B4%EB%A5%BC-%EC%9C%84%ED%95%9C-%EA%B0%80%EA%B3%84%EB%B6%80-%EC%95%B1-%EC%B6%94%EC%B2%9C-TOP-5"
    },
    {
     "kind": "티스토리",
     "title": "tistory.com",
     "url": "https://insuuy.tistory.com/21"
    },
    {
     "kind": "웹/블로그",
     "title": "appbiabi.com",
     "url": "https://appbiabi.com/account-book-top6/"
    },
    {
     "kind": "티스토리",
     "title": "tistory.com",
     "url": "https://s2ohxx.tistory.com/entry/%EC%82%AC%ED%9A%8C%EC%B4%88%EB%85%84%EC%83%9D%EC%9D%84-%EC%9C%84%ED%95%9C-%EA%B0%80%EA%B3%84%EB%B6%80-%EC%96%B4%ED%94%8C-%EB%B9%84%EA%B5%90-%EB%B0%8F-%EC%B6%94%EC%B2%9C"
    },
    {
     "kind": "웹/블로그",
     "title": "realbyteapps.com",
     "url": "https://ko.realbyteapps.com/"
    },
    {
     "kind": "웹/블로그",
     "title": "gongysd.com",
     "url": "https://gongysd.com/notion-budget/?bmode=view&idx=170109383"
    },
    {
     "kind": "티스토리",
     "title": "tistory.com",
     "url": "https://jjeongddol.tistory.com/57"
    },
    {
     "kind": "웹/블로그",
     "title": "google.com",
     "url": "https://play.google.com/store/apps/details?id=com.freeman.moneymanager&hl=ko"
    }
   ]
  },
  "el-01": {
   "q": "초등학생 스터디플래너 추천해줘",
   "kw": "초등스터디플래너",
   "line": "차일드라이크 초등",
   "mentioned": true,
   "searchQueries": [
    "초등학생 스터디플래너 추천",
    "초등학생 플래너 인기",
    "초등학생 공부 계획표 양식",
    "초등학생에게 적합한 스터디 플래너 특징"
   ],
   "brands": [
    "초등학생 스터디 플래너 추천 브랜드 및 제품",
    "리훈 (Rihun)",
    "인디고어린이 (Indigo Children)",
    "모트모트 (Motemote)",
    "초등학생 스터디 플래너 선택 시 고려사항",
    "학년별 맞춤",
    "자기 주도 학습 유도",
    "구성 및 디자인"
   ],
   "sources": [
    {
     "kind": "웹/블로그",
     "title": "rihoon.co.kr",
     "url": "https://m.rihoon.co.kr/category/%EC%B4%88%EB%93%B1%ED%95%99%EC%83%9D/227/"
    },
    {
     "kind": "웹/블로그",
     "title": "kakao.com",
     "url": "https://m.shoppinghow.kakao.com/m/search/q/%EC%9E%90%EA%B8%B0%EC%A3%BC%EB%8F%84%ED%95%99%EC%8A%B5%20%ED%94%8C%EB%9E%98%EB%84%88"
    },
    {
     "kind": "웹/블로그",
     "title": "aladin.co.kr",
     "url": "https://www.aladin.co.kr/shop/wbrowse.aspx?CID=251442"
    },
    {
     "kind": "유튜브",
     "title": "youtube.com",
     "url": "https://www.youtube.com/watch?v=u5_n3utTBcI"
    },
    {
     "kind": "유튜브",
     "title": "youtube.com",
     "url": "https://www.youtube.com/watch?v=xuSyleic25Q"
    },
    {
     "kind": "웹/블로그",
     "title": "kyobobook.co.kr",
     "url": "https://hottracks.kyobobook.co.kr/gift/detail/S000219446872"
    },
    {
     "kind": "티스토리",
     "title": "tistory.com",
     "url": "https://smartday01.tistory.com/entry/%EC%9E%90%EA%B8%B0%EC%A3%BC%EB%8F%84%ED%95%99%EC%8A%B5%EC%9D%84-%EC%9C%84%ED%95%9C-%EC%8A%A4%ED%84%B0%EB%94%94-%ED%94%8C%EB%9E%98%EB%84%88-%ED%99%9C%EC%9A%A9%EB%B2%95"
    },
    {
     "kind": "유튜브",
     "title": "youtube.com",
     "url": "https://www.youtube.com/watch?v=gZnAc1nncc4"
    }
   ]
  },
  "el-02": {
   "q": "초등 자기주도학습 플래너 추천해줘",
   "kw": "자기주도학습플래너",
   "line": "차일드라이크 초등",
   "mentioned": true,
   "searchQueries": [
    "초등 자기주도학습 플래너 추천",
    "초등학생 공부 플래너",
    "초등 학습 플래너 특징",
    "초등 플래너 사용법"
   ],
   "brands": [
    "추천 초등 자기주도학습 플래너",
    "랄라지니 초등 공부온도 스터디 플래너",
    "모트모트 플래너 (31일, 16주, 100일)",
    "리훈 곰부 초등학생 스터디플래너",
    "보니 스터디 플래너",
    "오늘의 날짜와 요일",
    "오늘의 목표",
    "해야 할 일 리스트 (To Do List)"
   ],
   "sources": [
    {
     "kind": "웹/블로그",
     "title": "kakao.com",
     "url": "https://m.shoppinghow.kakao.com/m/search/q/%EC%9E%90%EA%B8%B0%EC%A3%BC%EB%8F%84%ED%95%99%EC%8A%B5%20%ED%94%8C%EB%9E%98%EB%84%88"
    },
    {
     "kind": "웹/블로그",
     "title": "rihoon.co.kr",
     "url": "https://rihoon.co.kr/product/%EA%B3%B0%EB%B6%80-%EC%84%B8%EC%9A%B0%EB%8A%94-%EC%B4%88%EB%93%B1%ED%94%8C%EB%9E%98%EB%84%88-%EC%B4%88%EB%93%B1%ED%95%99%EC%83%9D-%EC%9E%90%EA%B8%B0%EC%A3%BC%EB%8F%84%ED%95%99%EC%8A%B5-%EA%B3%B5%EB%B6%80%EC%8A%B5%EA%B4%80-%EB%A7%8C%EB%93%A4%EA%B8%B0/625/"
    },
    {
     "kind": "웹/블로그",
     "title": "aladin.co.kr",
     "url": "https://www.aladin.co.kr/shop/wbrowse.aspx?CID=251442"
    },
    {
     "kind": "웹/블로그",
     "title": "danawa.com",
     "url": "https://search.danawa.com/dsearch.php?query=%EC%B4%88%EB%93%B1%20%EA%B3%B5%EB%B6%80%EC%8A%B5%EA%B4%80%20%EC%A0%80%ED%95%99%EB%85%84%20%EC%8A%A4%ED%84%B0%EB%94%94%ED%94%8C%EB%9E%98%EB%84%88"
    },
    {
     "kind": "유튜브",
     "title": "youtube.com",
     "url": "https://www.youtube.com/watch?v=u5_n3utTBcI"
    },
    {
     "kind": "웹/블로그",
     "title": "danawa.com",
     "url": "https://search.danawa.com/dsearch.php?query=%EC%9E%90%EA%B8%B0%EC%A3%BC%EB%8F%84%ED%95%99%EC%8A%B5%20%EB%8B%A4%EC%9D%B4%EC%96%B4%EB%A6%AC%20%ED%95%99%EC%83%9D%EC%9A%A9"
    },
    {
     "kind": "유튜브",
     "title": "youtube.com",
     "url": "https://www.youtube.com/watch?v=3qbRu_qU2ms"
    },
    {
     "kind": "티스토리",
     "title": "tistory.com",
     "url": "https://smartday01.tistory.com/entry/%EC%9E%90%EA%B8%B0%EC%A3%BC%EB%8F%84%ED%95%99%EC%8A%B5%EC%9D%84-%EC%9C%84%ED%95%9C-%EC%8A%A4%ED%84%B0%EB%94%94-%ED%94%8C%EB%9E%98%EB%84%88-%ED%99%9C%EC%9A%A9%EB%B2%95"
    }
   ]
  },
  "wk-01": {
   "q": "직장인 업무일지 추천해줘",
   "kw": "업무일지",
   "line": "업무/직장",
   "mentioned": false,
   "searchQueries": [
    "직장인 업무일지 추천",
    "업무일지 양식",
    "업무일지 작성법",
    "좋은 업무일지 특징",
    "업무일지 템플릿"
   ],
   "brands": [
    "업무일지 작성의 중요성 및 효과",
    "업무 현황 파악 및 효율적인 계획 수립.",
    "시간 관리 및 생산성 향상.",
    "업무 누락 방지 및 진행 상황 추적.",
    "개인의 근무 실적 및 성과를 객관적인 자료로 남김.",
    "팀 리포트 작성 및 동료와의 원활한 소통 지원.",
    "인수인계 시 유용한 자료로 활용.",
    "업무 패턴 파악 및 개선 방안 모색."
   ],
   "sources": [
    {
     "kind": "웹/블로그",
     "title": "shiftee.io",
     "url": "https://shiftee.io/ko/blog/article/how-to-write-a-work-journal-to-boost-your-work-productivity"
    },
    {
     "kind": "웹/블로그",
     "title": "boardmix.com",
     "url": "https://boardmix.com/kr/skills/how-to-write-my-worklog/"
    },
    {
     "kind": "웹/블로그",
     "title": "shoplworks.com",
     "url": "https://www.shoplworks.com/blog-templates/work-log-format"
    },
    {
     "kind": "웹/블로그",
     "title": "notion.com",
     "url": "https://www.notion.com/ko/templates/weekly-work-log"
    },
    {
     "kind": "티스토리",
     "title": "tistory.com",
     "url": "https://powered-by.tistory.com/entry/%EC%9D%BC%EC%9D%BC%EC%97%85%EB%AC%B4%EC%9D%BC%EC%A7%80-%EC%96%91%EC%8B%9D-%EC%97%85%EB%AC%B4%EC%9D%BC%EC%A7%80-%EC%9E%91%EC%84%B1%EB%B2%95-%EC%A3%BC%EC%9A%94-%EC%82%AC%ED%95%AD-%EB%B0%8F-%EA%B5%AC%EC%84%B1"
    },
    {
     "kind": "티스토리",
     "title": "tistory.com",
     "url": "https://cavalokori.tistory.com/entry/%ED%9A%A8%EC%9C%A8%EC%A0%81%EC%9D%B8-%EC%97%85%EB%AC%B4-%EC%9D%BC%EC%A7%80-%EC%9E%91%EC%84%B1%EB%B2%95-%EC%83%9D%EC%82%B0%EC%84%B1%EC%9D%84-%EB%86%92%EC%9D%B4%EB%8A%94-%ED%8C%81%EA%B3%BC-%EB%85%B8%ED%95%98%EC%9A%B0"
    },
    {
     "kind": "웹/블로그",
     "title": "bizforms.co.kr",
     "url": "https://www.bizforms.co.kr/bizcontents/hotclick/2016/20160425.asp"
    },
    {
     "kind": "웹/블로그",
     "title": "todoto.co.kr",
     "url": "https://www.todoto.co.kr/gallary-executionlab-action-delay/?bmode=view&idx=170864306"
    }
   ]
  },
  "rd-01": {
   "q": "독서기록장 추천해줘",
   "kw": "독서기록장",
   "line": "독서기록",
   "mentioned": true,
   "searchQueries": [
    "독서기록장 추천",
    "독서 기록 어플 추천",
    "독서 다이어리",
    "좋은 독서기록 방법"
   ],
   "brands": [
    "1. 독서 기록 앱 추천",
    "2. 종이 독서기록장 추천",
    "3. 효과적인 독서 기록을 위한 팁"
   ],
   "sources": [
    {
     "kind": "웹/블로그",
     "title": "theden.co.kr",
     "url": "https://www.theden.co.kr/news/articleView.html?idxno=2877"
    },
    {
     "kind": "티스토리",
     "title": "tistory.com",
     "url": "https://halsuitda.tistory.com/106"
    },
    {
     "kind": "웹/블로그",
     "title": "apple.com",
     "url": "https://apps.apple.com/kr/app/%EB%B6%81%EC%A0%81%EB%B6%81%EC%A0%81-%EB%8F%85%EC%84%9C-%EA%B8%B0%EB%A1%9D-%EC%95%B1/id1472538417"
    },
    {
     "kind": "웹/블로그",
     "title": "maily.so",
     "url": "https://maily.so/inspirex/posts/knrjm0v7rld"
    },
    {
     "kind": "티스토리",
     "title": "tistory.com",
     "url": "https://reading-log.tistory.com/8"
    },
    {
     "kind": "웹/블로그",
     "title": "rwnt.kr",
     "url": "https://rwnt.kr/shop/?idx=36"
    },
    {
     "kind": "웹/블로그",
     "title": "kyobobook.co.kr",
     "url": "https://hottracks.kyobobook.co.kr/gift/02/10/00"
    },
    {
     "kind": "웹/블로그",
     "title": "yes24.com",
     "url": "https://m.yes24.com/category/display/006001004063009"
    }
   ]
  },
  "ws-01": {
   "q": "필사하기 좋은 노트 추천해줘",
   "kw": "필사노트",
   "line": "필사/노트",
   "mentioned": false,
   "searchQueries": [
    "필사하기 좋은 노트 추천",
    "필사 노트 팁",
    "만년필 필사 노트 추천",
    "번짐 없는 노트 추천"
   ],
   "brands": [
    "만년필 사용자에게 특히 좋은 노트",
    "글입다 만년필 필사노트",
    "로디아(Rhodia)",
    "클레르퐁텐(Clairefontaine)",
    "미도리 MD 노트",
    "로이텀 1917",
    "엔드리스 레코더 (Regalia 종이)",
    "그 외 필사하기 좋은 노트"
   ],
   "sources": [
    {
     "kind": "웹/블로그",
     "title": "wearingeul.kr",
     "url": "https://wearingeul.kr/all/?idx=1390"
    },
    {
     "kind": "유튜브",
     "title": "youtube.com",
     "url": "https://www.youtube.com/watch?v=2vqIi4JzH9g"
    },
    {
     "kind": "티스토리",
     "title": "tistory.com",
     "url": "https://afterview.tistory.com/entry/%EB%A7%8C%EB%85%84%ED%95%84-%EB%85%B8%ED%8A%B8-%EB%B9%84%EA%B5%90%EB%9D%BC%EC%9D%B4%ED%94%84-%EA%B3%A0%EC%BF%A0%EC%9A%94-%EB%A7%88%EB%A3%A8%EB%A7%9D-%ED%81%B4%EB%A0%88%EB%A5%B4%ED%90%81%ED%85%90-%EA%B0%81%EB%8B%B7-%EC%95%84%EB%A5%B4%EB%94%94%EC%9B%80"
    },
    {
     "kind": "레딧",
     "title": "reddit.com",
     "url": "https://www.reddit.com/r/fountainpens/comments/1k62zo5/notebooks_with_no_ghosting/?tl=ko"
    },
    {
     "kind": "레딧",
     "title": "reddit.com",
     "url": "https://www.reddit.com/r/fountainpens/comments/1djn22q/any_recommendations_for_fp_friendly_pocket/?tl=ko"
    },
    {
     "kind": "티스토리",
     "title": "tistory.com",
     "url": "https://bovistaplumbeapers.tistory.com/71"
    },
    {
     "kind": "레딧",
     "title": "reddit.com",
     "url": "https://www.reddit.com/r/fountainpens/comments/1c1aj1b/notebook_suggestion_where_the_ink_doesnt_bleed/?tl=ko"
    },
    {
     "kind": "유튜브",
     "title": "youtube.com",
     "url": "https://www.youtube.com/watch?v=Amv64H-ehHk"
    }
   ]
  }
 }
}